gaomi/__init__.py
gaomi/dcm2nii.py
gaomi/getparams.py
gaomi/nrrd2nii.py
gaomi-0.0.1.dist-info/LICENSE
gaomi-0.0.1.dist-info/METADATA
gaomi-0.0.1.dist-info/WHEEL
gaomi-0.0.1.dist-info/top_level.txt
gaomi-0.0.1.dist-info/RECORD
