Metadata-Version: 2.1
Name: gaomi
Version: 0.0.1
Summary: A small medical image processing package
Home-page: https://github.com/vegetarianfish/gaomi
Author: Gao Hongjian
Author-email: hbtsqaghj@buaa.edu.cn
License: UNKNOWN
Platform: UNKNOWN
Classifier: Programming Language :: Python :: 3
Classifier: License :: OSI Approved :: MIT License
Classifier: Operating System :: OS Independent
License-File: LICENSE
